Metadata-Version: 1.0
Name: pkgTesting
Version: 1.0
Summary: something for testing
Home-page: UNKNOWN
Author: ramon
Author-email: ramon@abc.com
License: MIT
Platform: UNKNOWN
